{
  "meta": {
    "slug": "plumbing-and-bath",
    "sourceCsvFile": "plumbing-and-bath_2023-12-01_2026-04-01.csv",
    "mergedFromJson": "testing2.json",
    "generatedAt": "2026-04-03T05:09:37.036Z",
    "recallCount": 8
  },
  "recalls": [
    {
      "RecallID": 10436,
      "RecallNumber": "26026",
      "RecallDate": "2025-10-16T00:00:00",
      "Description": "This recall involves VST-brand residential wall-mounted gas boilers, Series VT, VR, and VR Plus, with model numbers VRS-150, VRS-199, VRP-150, VRP-199, VRS Plus-150, VRS Plus-199, VRP Plus-150, VRP Plus-199, VTS-150, VTS-199, VTP-150, and VTP-199. The white label on the side of the boiler has the model number bolded, near the top of the label. The boilers are metal, rectangular units and have either VST printed in white on the control panel near the bottom, or VESTA.DS.Inc. printed in gray near the top of the panel.",
      "URL": "https://www.cpsc.gov/Recalls/2026/VESTA-DS-Recalls-VST-Brand-Tankless-Water-Heaters-Due-to-Carbon-Monoxide-CO-Poisoning-Hazard-and-Risk-of-Serious-Injury-and-Death",
      "Title": "VESTA.DS Recalls VST Brand Tankless Water Heaters Due to Carbon Monoxide (CO) Poisoning Hazard and Risk of Serious Injury and Death",
      "ConsumerContact": "VESTA.DS toll-free at 888-505-5525 from 8:30 a.m. to 6 p.m. ET Monday through Friday, email condensingwaterheater@realtimeresults.net or online at www.recallrtr.com/condensingwaterheater or at https://www.vestahws.com and click on \"Recall\" under the \"Documents/Support\" tab at the top of the page for more information.",
      "LastPublishDate": "2025-10-17T00:00:00",
      "Products": [
        {
          "Name": "VST gas-fired tankless water heaters",
          "NumberOfUnits": "About 36,700 (In addition, about 3,500 were sold in Canada)"
        }
      ],
      "Inconjunctions": [
        {
          "URL": "https://recalls-rappels.canada.ca/en/alert-recall/vesta-tankless-hot-water-heater-recalled-due-carbon-monoxide-poisoning-hazard"
        }
      ],
      "Images": [
        {
          "URL": "https://www.cpsc.gov/s3fs-public/VR-VT-1.jpg",
          "Caption": "Recalled VR Plus and VT Series Vesta Water Heaters"
        },
        {
          "URL": "https://www.cpsc.gov/s3fs-public/VR-VT-2.jpg",
          "Caption": "Recalled VR Series Vesta Water Heater"
        },
        {
          "URL": "https://www.cpsc.gov/s3fs-public/VR-VT-3.png",
          "Caption": "Model Number on the Label of the Recalled Water Heaters"
        }
      ],
      "Injuries": [
        {
          "Name": "The firm has received 33 reports of cracked exhaust ducts allowing exhaust fumes to leak out. No injuries have been reported."
        }
      ],
      "Retailers": [
        {
          "Name": "In-store and online at Best Buy, Dick's Sporting Goods, Nebraska Furniture and ABT stores nationwide and online at nordictrack.com and Amazon.com from November 2018 through April 2022 for about $1,700."
        }
      ],
      "Importers": [
        {
          "Name": "VESTA.DS, Inc., of Ontario, California"
        }
      ],
      "SoldAtLabel": "Sold At",
      "ManufacturerCountries": [
        {
          "Country": "South Korea"
        }
      ],
      "Hazards": [
        {
          "Name": "The exhaust duct can crack, allowing gases to escape inside of the home, posing a carbon monoxide (CO) poisoning hazard that can result in death or serious injury."
        }
      ],
      "Remedies": [
        {
          "Name": "Consumers should immediately stop using the recalled water heater and contact VESTA.DS to have a certified technician install the free repair. Consumers who must continue using the water heater while awaiting repair should have working smoke and carbon monoxide alarms in their homes."
        }
      ],
      "RemedyOptions": [
        {
          "Option": "Repair"
        }
      ]
    },
    {
      "RecallID": 10289,
      "RecallNumber": "25307",
      "RecallDate": "2025-05-29T00:00:00",
      "Description": "This recall involves VFAUOSIT kitchen faucets, model number 06BNV. The faucets are brushed nickel, single-handle kitchen faucets with a pull-down detachable spray and single-hole installation. Consumers can identify whether they have a recalled faucet by searching their Amazon purchase history for \"Vfauosit\" and \"kitchen faucet\" and looking for a description including pull-down sprayer, brushed nickel, stainless steel modern, high-arc, single-handle, single-hole, pull-out kitchen faucet for bar laundry RV utility sink.",
      "URL": "https://www.cpsc.gov/Recalls/2025/VFAUOSIT-Brand-Kitchen-Faucets-Recalled-Due-to-Dangerous-Lead-Exposure-for-Young-Children-Sold-on-Amazon-com-by-Whisper08",
      "Title": "VFAUOSIT Brand Kitchen Faucets Recalled Due to Dangerous Lead Exposure for Young Children; Sold on Amazon.com by Whisper08",
      "ConsumerContact": "Whisper08 by email at customerservice@vfauosit.com.",
      "LastPublishDate": "2025-05-29T00:00:00",
      "Products": [
        {
          "Name": "VFAUOSIT Kitchen Faucets, model number 06BNV",
          "NumberOfUnits": "About 29,000"
        }
      ],
      "Images": [
        {
          "URL": "https://www.cpsc.gov/s3fs-public/VFAUOSIT.png",
          "Caption": "Recalled VFAUOSIT Kitchen Faucet"
        }
      ],
      "Injuries": [
        {
          "Name": "None reported"
        }
      ],
      "Manufacturers": [
        {
          "Name": "Jiang men cai nuo wei yu you xian gong si, of China, doing business as Amazon seller Whisper08"
        }
      ],
      "Retailers": [
        {
          "Name": "Online at www.amazon.com from January 2024 through May 2025 for about $40."
        }
      ],
      "SoldAtLabel": "Sold At",
      "ManufacturerCountries": [
        {
          "Country": "China"
        }
      ],
      "Hazards": [
        {
          "Name": "The recalled faucets were tested and found to contain lead that can leach into water at levels that can be particularly harmful to infants and young children. The faucets were also found to leach other contaminants. Lead ingestion can cause harmful neurological effects on infants and young children, including attention-related behavioral problems, decreased cognitive performance and lower IQ."
        }
      ],
      "Remedies": [
        {
          "Name": "Consumers should immediately stop using these faucets and contact Whisper08 about disposal and a refund. Consumers will need to provide a photograph of disposal and their order number to receive the refund. Whisper08 is contacting all known purchasers directly. Until these faucets can be replaced, consumers should only consume water from the faucets after running the water for 15 seconds."
        }
      ],
      "RemedyOptions": [
        {
          "Option": "Refund"
        }
      ]
    },
    {
      "RecallID": 10288,
      "RecallNumber": "25306",
      "RecallDate": "2025-05-29T00:00:00",
      "Description": "This recall involves KICIMPRO kitchen faucets, model number KM800-01-06BN. The faucets are brushed nickel, single-handle kitchen faucets with a pull-down detachable spray and single-hole installation. Consumers can identify whether they have a recalled faucet by searching their Amazon purchase history for \"Kicimpro\" and \"kitchen faucet\" and looking for a description including pull-down sprayer, brushed nickel, high-arc, single-handle sink faucet with water lines, commercial modern RV stainless steel, grifos de cocina.",
      "URL": "https://www.cpsc.gov/Recalls/2025/KICIMPRO-Brand-Kitchen-Faucets-Recalled-Due-to-Dangerous-Lead-Exposure-for-Young-Children-Sold-on-Amazon-com-by-Kicimpro",
      "Title": "KICIMPRO Brand Kitchen Faucets Recalled Due to Dangerous Lead Exposure for Young Children; Sold on Amazon.com by Kicimpro",
      "ConsumerContact": "Kicimpro by email at support@kicimprohome.com.",
      "LastPublishDate": "2025-05-29T00:00:00",
      "Products": [
        {
          "Name": "KICIMPRO Kitchen Faucets, model number KM800-01-06BN",
          "NumberOfUnits": "About 50,000"
        }
      ],
      "Images": [
        {
          "URL": "https://www.cpsc.gov/s3fs-public/KICIMPRO.jpg",
          "Caption": "Recalled KICIMPRO Kitchen Faucet"
        }
      ],
      "Injuries": [
        {
          "Name": "None reported"
        }
      ],
      "Manufacturers": [
        {
          "Name": "Kaipingshikemuyulinweiyushiyeyouxiangongsi, of China, doing business as Amazon seller Kicimpro"
        }
      ],
      "Retailers": [
        {
          "Name": "Online at www.amazon.com from January 2024 through May 2025 for about $35."
        }
      ],
      "SoldAtLabel": "Sold At",
      "ManufacturerCountries": [
        {
          "Country": "China"
        }
      ],
      "Hazards": [
        {
          "Name": "The recalled faucets were tested and found to contain lead that can leach into water at levels that can be particularly harmful to infants and young children. Lead ingestion can cause harmful neurological effects on infants and young children, including attention-related behavioral problems, decreased cognitive performance and lower IQ."
        }
      ],
      "Remedies": [
        {
          "Name": "Consumers should immediately stop using these faucets and contact Kicimpro about disposal and a refund. Consumers will need to provide a photograph of disposal and their order number to receive the refund. Kicimpro is contacting all known purchasers directly. Until these faucets can be replaced, consumers should only consume water from the faucets after running the water for 15 seconds."
        }
      ],
      "RemedyOptions": [
        {
          "Option": "Refund"
        }
      ]
    },
    {
      "RecallID": 10287,
      "RecallNumber": "25305",
      "RecallDate": "2025-05-29T00:00:00",
      "Description": "This recall involves BASDEHEN kitchen faucets, model number CFDTTH-000-YGH. The faucets are matte black single-handle kitchen faucets with 360° swivel, spring spout design, detachable spray, optional mounting plate and single-hole installation. Consumers can identify whether they have a recalled faucet by searching their Amazon purchase history for \"Basdehen\" and \"kitchen faucet.\"",
      "URL": "https://www.cpsc.gov/Recalls/2025/BASDEHEN-Brand-Kitchen-Faucets-Recalled-Due-to-Dangerous-Lead-Exposure-for-Young-Children-Sold-on-Amazon-com-by-Chenfeng-Store",
      "Title": "BASDEHEN Brand Kitchen Faucets Recalled Due to Dangerous Lead Exposure for Young Children; Sold on Amazon.com by Chenfeng Store",
      "ConsumerContact": "Chenfeng Store by email at ChenfengStoreF@outlook.com.",
      "LastPublishDate": "2025-05-29T00:00:00",
      "Products": [
        {
          "Name": "BASDEHEN Kitchen Faucets, model number CFDTTH-000-YGH",
          "NumberOfUnits": "About 24,000"
        }
      ],
      "Images": [
        {
          "URL": "https://www.cpsc.gov/s3fs-public/Basdehen.jpg",
          "Caption": "Recalled BASDEHEN Kitchen Faucet"
        }
      ],
      "Injuries": [
        {
          "Name": "None reported"
        }
      ],
      "Manufacturers": [
        {
          "Name": "Ruianshichenfengwujinzhizaoyouxiangongsi, of China, doing business as Amazon seller Chenfeng Store"
        }
      ],
      "Retailers": [
        {
          "Name": "Online at www.amazon.com from May 2024 through May 2025 for about $30."
        }
      ],
      "SoldAtLabel": "Sold At",
      "ManufacturerCountries": [
        {
          "Country": "China"
        }
      ],
      "Hazards": [
        {
          "Name": "The recalled faucets were tested and found to contain lead that can leach into water at levels that can be particularly harmful to infants and young children. The faucets were also found to leach other contaminants. Lead ingestion can cause harmful neurological effects on infants and young children, including attention-related behavioral problems, decreased cognitive performance and lower IQ."
        }
      ],
      "Remedies": [
        {
          "Name": "Consumers should immediately stop using these faucets and contact Chenfeng Store about disposal and a refund. Consumers will need to provide a photograph of disposal to receive the refund. Amazon is contacting all known purchasers directly. Until these faucets can be replaced, consumers should only consume water from the faucets after running the water for 15 seconds."
        }
      ],
      "RemedyOptions": [
        {
          "Option": "Refund"
        }
      ]
    },
    {
      "RecallID": 10060,
      "RecallNumber": "24378",
      "RecallDate": "2024-09-26T00:00:00",
      "Description": "The recall involves Multi-Grip Tub Safety Bars sold under the brands Peerless, model PL585; Safety First, models SF585 and S1F585; and Delta, model DF585. The recalled Multi-Grip Tub Safety Bars are powder-coated aluminum, were sold in the color white, and feature a one-inch diameter tube with two gripping surfaces at about 8 inches and 15 inches. The model number and brand name are listed on a label on the product's packaging.",
      "URL": "https://www.cpsc.gov/Recalls/2024/Liberty-Hardware-Recalls-Multi-Grip-Tub-Safety-Bars-Due-to-Fall-Hazard",
      "Title": "Liberty Hardware Recalls Multi-Grip Tub Safety Bars Due to Fall Hazard",
      "ConsumerContact": "Liberty Hardware toll-free at 844-811-4541 from 9 a.m. to 5 p.m. ET from Monday through Friday, email at recall@libertyhardware.com, or online at www.libertyhardware.com/recall-notices/tub-safety-bar or www.libertyhardware.com and click on \"RECALL NOTICE\" on the bottom right of the website.",
      "LastPublishDate": "2024-09-26T00:00:00",
      "Products": [
        {
          "Name": "Multi-Grip Tub Safety Bars",
          "NumberOfUnits": "About 174,500"
        }
      ],
      "Images": [
        {
          "URL": "https://www.cpsc.gov/s3fs-public/tubsafetybar.png",
          "Caption": "Recalled Multi-Grip Tub Safety Bar"
        }
      ],
      "Injuries": [
        {
          "Name": "Liberty Hardware has received fourteen reports of the plastic sticker grip pads becoming dislodged after installation or otherwise needing replacement, including one fall with a minor injury reported."
        }
      ],
      "Retailers": [
        {
          "Name": "Ace Hardware, The Home Depot, Lowe's, Menards, Walmart, and other hardware and plumbing stores and suppliers nationwide, and online at Amazon.com and FlyingBulldogs.com from January 2011 through May 2024 for between $16 and $55."
        }
      ],
      "Importers": [
        {
          "Name": "Liberty Hardware Manufacturing Corp., of Winston-Salem, North Carolina"
        }
      ],
      "SoldAtLabel": "Sold At",
      "ManufacturerCountries": [
        {
          "Country": "China"
        }
      ],
      "Hazards": [
        {
          "Name": "The plastic sticker grip pads can become dislodged after installation on tubs with tapered side walls, making the recalled Multi-Grip Tub Safety Bars unstable during use, posing a fall hazard."
        }
      ],
      "Remedies": [
        {
          "Name": "Consumers should immediately stop using the recalled Multi-Grip Tub Safety Bars and contact Liberty Hardware. Consumers can request to receive a pre-paid label and free packaging to return the Multi-Grip Tub Safety Bars for a $35 refund."
        }
      ],
      "RemedyOptions": [
        {
          "Option": "Refund"
        }
      ]
    },
    {
      "RecallID": 10046,
      "RecallNumber": "24359",
      "RecallDate": "2024-09-12T00:00:00",
      "Description": "The spa pumps could have been sold separately, or in a package with an inflatable spa liner in different colors, styles, and inflatable spa sizes. The inflatable spa liners packaged with the pumps are sold under the brand names SaluSpa, Coleman, and Hydro-Force, which are printed on the side of the liner. This recall only includes AirJet and HydroJet Spa Pump model numbers P05332, P05339, P05711, P05807, P07000, P07001, P05511, P07034, and P07572. \"Bestway\" and the model number are printed on the label on the side or back of the spa pump.",
      "URL": "https://www.cpsc.gov/Recalls/2024/About-866000-AirJet-and-HydroJet-Spa-Pumps-Recalled-Due-to-Fire-Hazard-One-Death-Reported-Manufactured-by-Bestway-and-Sold-with-SaluSpa-Coleman-and-Hydro-Force-Spa-Liners",
      "Title": "About 866,000 AirJet and HydroJet Spa Pumps Recalled Due to Fire Hazard; One Death Reported; Manufactured by Bestway and Sold with SaluSpa, Coleman, and Hydro-Force Spa Liners",
      "ConsumerContact": "Bestway toll-free at 888-943-2396 from 8 a.m. to 5 p.m. ET Monday through Friday, or online at www.bestwayusa.com/product-safety-and-recall or www.bestwayusa.com and click on \"Recall and Safety\" on the bottom of the page for more information.",
      "LastPublishDate": "2024-09-12T00:00:00",
      "Products": [
        {
          "Name": "AirJet and HydroJet Spa Pumps",
          "NumberOfUnits": "About 866,000"
        }
      ],
      "Inconjunctions": [
        {
          "URL": "https://recalls-rappels.canada.ca/en/alert-recall/airjet-and-hydrojet-spa-pumps-recalled-due-fire-hazard"
        }
      ],
      "Images": [
        {
          "URL": "https://www.cpsc.gov/s3fs-public/airjet-spa-pump.png",
          "Caption": "Recalled AirJet Spa Pump"
        },
        {
          "URL": "https://www.cpsc.gov/s3fs-public/hydrojet-spa-pump.png",
          "Caption": "Recalled HydroJet Spa Pump"
        },
        {
          "URL": "https://www.cpsc.gov/s3fs-public/airjet-label.jpg",
          "Caption": "Recalled AirJet Spa Pump model number located on label on side of unit"
        },
        {
          "URL": "https://www.cpsc.gov/s3fs-public/hydrojet-label.jpg",
          "Caption": "Recalled HydroJet Spa Pump model number located on label on back of unit"
        },
        {
          "URL": "https://www.cpsc.gov/s3fs-public/spa-pump-liner.jpg",
          "Caption": "Recalled Spa Pump attached to inflatable spa liner"
        }
      ],
      "Injuries": [
        {
          "Name": "CPSC is aware of at least three fires reportedly involving the spa pumps, including one house fire that occurred in January 2024 in Kansas City, Missouri, which resulted in a fatality, and one additional fire that resulted in significant property damage. No additional injuries have been reported. There are seven additional incidents reportedly involving the spa pumps, which are currently under investigation. At this time no injuries have been reported with these additional incidents."
        }
      ],
      "Manufacturers": [
        {
          "Name": "Bestway (Hong Kong) International Ltd., of China"
        }
      ],
      "Retailers": [
        {
          "Name": "The recalled spa pumps were sold together with spa liners online at Bestway USA, Amazon, Costco, Walmart, Sam's Club, QVC, RuralKing and Spreetail, and at other stores nationwide from May 2021 through May 2024 for between $400 and $790."
        }
      ],
      "SoldAtLabel": "Sold At",
      "ManufacturerCountries": [
        {
          "Country": "China"
        }
      ],
      "Hazards": [
        {
          "Name": "The recalled AirJet and HydroJet spa pumps can overheat causing the plastic housing to ignite, posing a fire hazard."
        }
      ],
      "Remedies": [
        {
          "Name": "Consumers should immediately stop using the recalled spa pumps, and contact Bestway to receive a free replacement spa pump or a refund of $100 for AirJet spa pumps, or $189 for HydroJet spa pumps."
        }
      ],
      "RemedyOptions": [
        {
          "Option": "Refund"
        },
        {
          "Option": "Replace"
        }
      ]
    },
    {
      "RecallID": 9874,
      "RecallNumber": "24137",
      "RecallDate": "2024-02-29T00:00:00",
      "Description": "This recall involves certain Camplux brand portable tankless water heaters with model numbers AY132, BD158, BW211, BW264, and BW422, with the following sizes and manufacturing dates: Model Product Details Manufacture Date AY132 5L 1.32 GPM 34,000 btu/hr On or before September 17, 2021 BD158 6L 1.58 GPM 41,000 btu/hr On or before November 17, 2021 BW211 8L 2.11 GPM 55,000 btu/hr On or before November 17, 2021 BW264 12.8L 2.64 GPM 68,000 btu/hr On or before November 17, 2021 BW422 16L 4.22 GPM 110,000 btu/hr On or before December 20, 2021 These water heaters were designed and intended for outdoor use with an attached propane tank to quickly heat water for showering or other hot water needs. The water heaters were sold in white, black, and silver/gray colors. The \"Camplux\" logo is printed on the front of the unit. The product label is located on the side of the unit and includes the model, size and other product details, serial numbers, and brand information. Consumers will be directed to take a photograph of the label on their Camplux water heater product and send to Camplux to confirm that they have a recalled water heater to receive the replacement gas regulator.",
      "URL": "https://www.cpsc.gov/Recalls/2024/The-Home-Appliances-Recalls-Camplux-Brand-Portable-Tankless-Water-Heaters-Due-to-Fire-Hazard",
      "Title": "The Home Appliances Recalls Camplux Brand Portable Tankless Water Heaters Due to Fire Hazard",
      "ConsumerContact": "The Home Appliances (\"Camplux\") toll-free at 844-538-7475 from 9 a.m. to 5 p.m. ET Monday through Friday, email at support@camplux.com, online at www.thehomeappliances.com and click on \"Recalls\" or www.thehomeappliances.com/waterheaterrecall for more information.",
      "LastPublishDate": "2024-02-29T00:00:00",
      "Products": [
        {
          "Name": "Camplux portable tankless water heaters",
          "NumberOfUnits": "About 42,000"
        }
      ],
      "Images": [
        {
          "URL": "https://www.cpsc.gov/s3fs-public/Camplux-AY132-white_0.png",
          "Caption": "Recalled Camplux brand AY132 portable tankless water heater – white"
        },
        {
          "URL": "https://www.cpsc.gov/s3fs-public/Camplux-AY132-black_0.png",
          "Caption": "Recalled Camplux brand AY132 portable tankless water heater – black"
        },
        {
          "URL": "https://www.cpsc.gov/s3fs-public/Camplux-AY132-gray_0.png",
          "Caption": "Recalled Camplux brand AY132 portable tankless water heater – gray/silver"
        },
        {
          "URL": "https://www.cpsc.gov/s3fs-public/Camplux-BD158_0.png",
          "Caption": "Recalled Camplux brand BD158 portable tankless water heater"
        },
        {
          "URL": "https://www.cpsc.gov/s3fs-public/Camplux-BW211-white_0.png",
          "Caption": "Recalled Camplux brand BW211 portable tankless water heater – white"
        },
        {
          "URL": "https://www.cpsc.gov/s3fs-public/Camplux-BW211-gray_0.png",
          "Caption": "Recalled Camplux brand BW211 portable tankless water heater – gray/silver"
        },
        {
          "URL": "https://www.cpsc.gov/s3fs-public/Camplux-BW264_0.png",
          "Caption": "Recalled Camplux brand BW264 portable tankless water heater"
        },
        {
          "URL": "https://www.cpsc.gov/s3fs-public/Camplux-BW422_0.png",
          "Caption": "Recalled Camplux brand BW422 portable tankless water heater"
        }
      ],
      "Injuries": [
        {
          "Name": "Camplux has received 19 reports of fire incidents involving the recalled water heaters. No injuries have been reported."
        }
      ],
      "Retailers": [
        {
          "Name": "Online at Amazon.com and Walmart.com from June 2018 through December 2021 for between $160 and $400."
        }
      ],
      "Importers": [
        {
          "Name": "The Home Appliances Inc., d/b/a Camplux, of North Charleston, South Carolina"
        }
      ],
      "SoldAtLabel": "Sold At",
      "ManufacturerCountries": [
        {
          "Country": "China"
        }
      ],
      "Hazards": [
        {
          "Name": "The portable water heaters can leak gas from the gas regulator connection, posing a fire hazard."
        }
      ],
      "Remedies": [
        {
          "Name": "Consumers should immediately turn off and stop using the recalled portable water heaters and contact The Home Appliances for a free repair kit. The repair kit consists of a replacement gas regulator with a quick connect attachment that allows for easy connection and disconnection without the need to screw in the gas regulator. Instructions for installing this repair kit will also be provided."
        }
      ],
      "RemedyOptions": [
        {
          "Option": "Repair"
        }
      ]
    },
    {
      "RecallID": 9826,
      "RecallNumber": "24086",
      "RecallDate": "2024-01-18T00:00:00",
      "Description": "This recall involves wall-mounted, folding shower seats made of teak wood slats joined together by support rods that extend from two wall-mounting brackets. The recalled Tilt-Up Bath & Shower Seats have model numbers SBS-101BN, SBS-101PN, SBS-101PC or SBS-101ORB and have brushed nickel, polished nickel, polished chrome or oil-rubbed bronze finishes on the support rods and bracket covers. The recalled Tilt-Up Bath & Shower Seats measure 20 inches wide by 13 inches deep.",
      "URL": "https://www.cpsc.gov/Recalls/2024/Steamist-Recalls-Wall-Mounted-Tilt-Up-Bath-Shower-Seats-Due-to-Fall-and-Laceration-Hazards",
      "Title": "Steamist Recalls Wall-Mounted Tilt-Up Bath & Shower Seats Due to Fall and Laceration Hazards",
      "ConsumerContact": "Steamist toll-free at 866-968-2250 from 8 a.m. to 5 p.m. ET Monday through Friday, recall@steamist.com, or online at www.steamist.com/recall-notices or www.steamist.com and click on \"Recall Notices\" at the bottom of the website for more information.",
      "LastPublishDate": "2024-01-18T00:00:00",
      "Products": [
        {
          "Name": "Tilt-Up Bath & Shower Seats",
          "NumberOfUnits": "About 3,900 (In addition, about 733 were sold in Canada and about 126 were sold in Mexico)"
        }
      ],
      "Inconjunctions": [
        {
          "URL": "https://recalls-rappels.canada.ca/en/alert-recall/steamist-tilt-bath-shower-seat-recalled-due-potential-fall-and-laceration-hazard"
        }
      ],
      "Images": [
        {
          "URL": "https://www.cpsc.gov/s3fs-public/image3_40.png",
          "Caption": "Recalled Tilt-Up Bath & Shower Seat with brushed nickel finish"
        },
        {
          "URL": "https://www.cpsc.gov/s3fs-public/image2_38.png",
          "Caption": "Recalled Tilt-Up Bath & Shower Seat with polished nickel finish"
        },
        {
          "URL": "https://www.cpsc.gov/s3fs-public/image5_13.png",
          "Caption": "Recalled Tilt-Up Bath & Shower Seat with polished chrome finish"
        },
        {
          "URL": "https://www.cpsc.gov/s3fs-public/image4_26.png",
          "Caption": "Recalled Tilt-Up Bath & Shower Seat with oil-rubbed bronze finish"
        }
      ],
      "Injuries": [
        {
          "Name": "The firm has received 62 reports of the shower seats breaking, including 4 reports of injuries."
        }
      ],
      "Retailers": [
        {
          "Name": "Specialty plumbing supply outlets in the United States, Canada and Mexico from June 2009 through February 2015 for between $490 and $660."
        }
      ],
      "Importers": [
        {
          "Name": "Steamist Inc., of East Rutherford, New Jersey"
        }
      ],
      "SoldAtLabel": "Sold At",
      "ManufacturerCountries": [
        {
          "Country": "China"
        }
      ],
      "Hazards": [
        {
          "Name": "The wall mounting bracket and seat rods supporting the Tilt-Up Bath & Shower Seat can corrode and break, posing fall and laceration hazards."
        }
      ],
      "Remedies": [
        {
          "Name": "Consumers should immediately stop using the recalled shower seats and contact Steamist to determine if their product is included in the recall and for instructions for how to participate in the recall."
        }
      ],
      "RemedyOptions": [
        {
          "Option": "Refund"
        }
      ]
    }
  ]
}